techid_to_attack_nav/__init__.py
techid_to_attack_nav/cli.py
techid_to_attack_nav/core.py
techid_to_attack_nav/template.py
techid_to_attack_nav-2.0.1.dist-info/AUTHORS.rst
techid_to_attack_nav-2.0.1.dist-info/LICENSE
techid_to_attack_nav-2.0.1.dist-info/METADATA
techid_to_attack_nav-2.0.1.dist-info/WHEEL
techid_to_attack_nav-2.0.1.dist-info/entry_points.txt
techid_to_attack_nav-2.0.1.dist-info/top_level.txt
techid_to_attack_nav-2.0.1.dist-info/RECORD
