Metadata-Version: 2.1
Name: techid-to-attack-nav
Version: 2.0.1
Summary: A Python CLI utility for quickly converting a list or text file of MITRE ATT&CK technique IDs to a MITRE ATT&CK Navigator layer .JSON file.
Home-page: https://github.com/infosecb/techid_to_attack_nav
Author: Brendan Chamberlain
Author-email: brendan@infosecb.com
License: MIT license
Keywords: techid_to_attack_nav
Platform: UNKNOWN
Classifier: Development Status :: 2 - Pre-Alpha
Classifier: Intended Audience :: Developers
Classifier: License :: OSI Approved :: MIT License
Classifier: Natural Language :: English
Classifier: Programming Language :: Python :: 3
Classifier: Programming Language :: Python :: 3.5
Classifier: Programming Language :: Python :: 3.6
Classifier: Programming Language :: Python :: 3.7
Classifier: Programming Language :: Python :: 3.8
Requires-Python: >=3.5
